{
  "status": "0000",
  "data": {
    "total_p": "88.00000000",
    "in_use_p": "0.00000000",
    "available_p": "88.00000000",
    "xcoin_last_p": "0",
    "total_bm": "3599.00000000",
    "in_use_bm": "0.00000000",
    "available_bm": "3599.00000000",
    "xcoin_last_bm": "0",
    "total_krw": "1.408493",
    "in_use_krw": "0.00000000",
    "available_krw": "1.40849300",
    "total_btc": "0.00003332",
    "in_use_btc": "0.00000000",
    "available_btc": "0.00003332",
    "xcoin_last_btc": "57265000",
    "total_eth": "0.000000000000000000",
    "in_use_eth": "0.00000000",
    "available_eth": "0.00000000",
    "xcoin_last_eth": "3086000",
    "total_dash": "0.00000000",
    "in_use_dash": "0.00000000",
    "available_dash": "0.00000000",
    "xcoin_last_dash": "0",
    "total_ltc": "0.00000000",
    "in_use_ltc": "0.00000000",
    "available_ltc": "0.00000000",
    "xcoin_last_ltc": "0",
    "total_etc": "0.001000000000000000",
    "in_use_etc": "0.00000000",
    "available_etc": "0.00100000",
    "xcoin_last_etc": "29830",
    "total_xrp": "0.00000031",
    "in_use_xrp": "0.00000000",
    "available_xrp": "0.00000031",
    "xcoin_last_xrp": "833",
    "total_bch": "0.00000000",
    "in_use_bch": "0.00000000",
    "available_bch": "0.00000000",
    "xcoin_last_bch": "352700",
    "total_xmr": "0.000000000000",
    "in_use_xmr": "0.00000000",
    "available_xmr": "0.00000000",
    "xcoin_last_xmr": "0",
    "total_zec": "0.00000000",
    "in_use_zec": "0.00000000",
    "available_zec": "0.00000000",
    "xcoin_last_zec": "0",
    "total_qtum": "0.00000000",
    "in_use_qtum": "0.00000000",
    "available_qtum": "0.00000000",
    "xcoin_last_qtum": "5045",
    "total_btg": "0.00000000",
    "in_use_btg": "0.00000000",
    "available_btg": "0.00000000",
    "xcoin_last_btg": "28760",
    "total_eos": "0.00000000",
    "in_use_eos": "0.00000000",
    "available_eos": "0.00000000",
    "xcoin_last_eos": "1155",
    "total_icx": "0.000000000000000000",
    "in_use_icx": "0.00000000",
    "available_icx": "0.00000000",
    "xcoin_last_icx": "359",
    "total_ven": "0.000000000000000000",
    "in_use_ven": "0.00000000",
    "available_ven": "0.00000000",
    "xcoin_last_ven": "0",
    "total_trx": "0.00006275",
    "in_use_trx": "0.00000000",
    "available_trx": "0.00006275",
    "xcoin_last_trx": "147",
    "total_elf": "0.00000000",
    "in_use_elf": "0.00000000",
    "available_elf": "0.00000000",
    "xcoin_last_elf": "787",
    "total_mith": "0.000000000000000000",
    "in_use_mith": "0.00000000",
    "available_mith": "0.00000000",
    "xcoin_last_mith": "0",
    "total_mco": "0.00000000",
    "in_use_mco": "0.00000000",
    "available_mco": "0.00000000",
    "xcoin_last_mco": "0",
    "total_omg": "0.000000000000000000",
    "in_use_omg": "0.00000000",
    "available_omg": "0.00000000",
    "xcoi
    n_last_omg
    ":"
    0
    ","
    total_knc
    ":"
    0.000000000000000000
    ","
    in_use_knc
    ":"
    0.00000000
    ","
    available_knc
    ":"
    0.00000000
    ","
    xcoin_last_knc
    ":"
    956
    ","
    total_glm
    ":"
    0.0
    00000000000000000
    ","
    in_use_glm
    ":"
    0.00000000
    ","
    available_glm
    ":"
    0.00000000
    ","
    xcoin_last_glm
    ":"
    325
    ","
    total_hsr
    ":"
    0.00000000
    ","
    in_use_hsr
    ":"
    0.0000000
    0
    ","
    available_hsr
    ":"
    0.00000000
    ","
    xcoin_last_hsr
    ":"
    0
    ","
    total_zil
    ":"
    0.000000000000
    ","
    in_use_zil
    ":"
    0.00000000
    ","
    available_zil
    ":"
    0.00000000
    ","
    xcoin_l
    ast_zil
    ":"
    33.84
    ","
    total_ethos
    ":"
    0.00000000
    ","
    in_use_ethos
    ":"
    0.00000000
    ","
    available_ethos
    ":"
    0.00000000
    ","
    xcoin_last_ethos
    ":"
    0
    ","
    total_pay
    ":"
    0.0000
    00000000000000
    ","
    in_use_pay
    ":"
    0.00000000
    ","
    available_pay
    ":"
    0.00000000
    ","
    xcoin_last_pay
    ":"
    0
    ","
    total_waxp
    ":"
    0.00000000
    ","
    in_use_waxp
    ":"
    0.00000000
    ",
    "available_waxp": "0.00000000",
    "xcoin_last_waxp": "95.28",
    "total_powr": "0.00000000",
    "in_use_powr": "0.00000000",
    "available_powr": "0.00000000",
    "xcoin
    _last_powr
    ":"
    504
    ","
    total_lrc
    ":"
    0.000000000000000000
    ","
    in_use_lrc
    ":"
    0.00000000
    ","
    available_lrc
    ":"
    0.00000000
    ","
    xcoin_last_lrc
    ":"
    412
    ","
    total_gto
    ":"
    0
    .00000000
    ","
    in_use_gto
    ":"
    0.00000000
    ","
    available_gto
    ":"
    0.00000000
    ","
    xcoin_last_gto
    ":"
    0
    ","
    total_pch
    ":"
    0.000000000000000000
    ","
    in_use_pch
    ":"
    0.0000000
    0
    ","
    available_pch
    ":"
    0.00000000
    ","
    xcoin_last_pch
    ":"
    0
    ","
    total_eosdac
    ":"
    0.00000000
    ","
    in_use_eosdac
    ":"
    0.00000000
    ","
    available_eosdac
    ":"
    0.00000000
    ","
    xc
    oin_last_eosdac
    ":"
    0
    ","
    total_steem
    ":"
    0.00000000
    ","
    in_use_steem
    ":"
    0.00000000
    ","
    available_steem
    ":"
    0.00000000
    ","
    xcoin_last_steem
    ":"
    344
    ","
    total_strax
    ": "0.00000000",
    "in_use_strax": "0.00000000",
    "available_strax": "0.00000000",
    "xcoin_last_strax": "1327",
    "total_ae": "0.000000000000000000",
    "in_use_ae": "0.00000000",
    "available_ae": "0.00000000",
    "xcoin_last_ae": "0",
    "total_zrx": "0.000050000000000000",
    "in_use_zrx": "0.00000000",
    "available_zrx": "0.0000
    5000
    ","
    xcoin_last_zrx
    ":"
    504
    ","
    total_rep
    ":"
    0.000000000000000000
    ","
    in_use_rep
    ":"
    0.00000000
    ","
    available_rep
    ":"
    0.00000000
    ","
    xcoin_last_rep
    ":"
    0
    ","
    tota
    l_xem
    ":"
    0.00000000
    ","
    in_use_xem
    ":"
    0.00000000
    ","
    available_xem
    ":"
    0.00000000
    ","
    xcoin_last_xem
    ":"
    0
    ","
    total_snt
    ":"
    0.000000000000000000
    ","
    in_use_snt
    ":"
    0.00000000
    ","
    available_snt
    ":"
    0.00000000
    ","
    xcoin_last_snt
    ":"
    60.97
    ","
    total_ada
    ":"
    0.00000000
    ","
    in_use_ada
    ":"
    0.00000000
    ","
    available_ada
    ":"
    0.00000000
    ",
    "xcoin_last_ada": "807",
    "total_ppt": "0.00000000",
    "in_use_ppt": "0.00000000",
    "available_ppt": "0.00000000",
    "xcoin_last_ppt": "0",
    "total_ctxc": "0.0000
    48344370860927
    ","
    in_use_ctxc
    ":"
    0.00000000
    ","
    available_ctxc
    ":"
    0.00004834
    ","
    xcoin_last_ctxc
    ":"
    578
    ","
    total_bat
    ":"
    0.000000000000000000
    ","
    in_use_bat
    ":
    "0.00000000",
    "available_bat": "0.00000000",
    "xcoin_last_bat": "349",
    "total_wtc": "0.000000000000000000",
    "in_use_wtc": "0.00000000",
    "available_wtc": "0.
    00000000
    ","
    xcoin_last_wtc
    ":"
    0
    ","
    total_cmt
    ":"
    0.000000000000000000
    ","
    in_use_cmt
    ":"
    0.00000000
    ","
    available_cmt
    ":"
    0.00000000
    ","
    xcoin_last_cmt
    ":"
    0
    ","
    to
    tal_theta
    ":"
    0.000000000000000000
    ","
    in_use_theta
    ":"
    0.00000000
    ","
    available_theta
    ":"
    0.00000000
    ","
    xcoin_last_theta
    ":"
    1727
    ","
    total_poly
    ":"
    0.0000000000
    00000000
    ","
    in_use_poly
    ":"
    0.00000000
    ","
    available_poly
    ":"
    0.00000000
    ","
    xcoin_last_poly
    ":"
    0
    ","
    total_loom
    ":"
    0.000000000000000000
    ","
    in_use_loom
    ":"
    0.000
    00000
    ","
    available_loom
    ":"
    0.00000000
    ","
    xcoin_last_loom
    ":"
    144
    ","
    total_cvc
    ":"
    0.000000000000000000
    ","
    in_use_cvc
    ":"
    0.00000000
    ","
    available_cvc
    ":"
    0.0000
    0000
    ","
    xcoin_last_cvc
    ":"
    0
    ","
    total_man
    ":"
    0.000000000000000000
    ","
    in_use_man
    ":"
    0.00000000
    ","
    available_man
    ":"
    0.00000000
    ","
    xcoin_last_man
    ":"
    0
    ","
    total_
    waves
    ":"
    0.00000000
    ","
    in_use_waves
    ":"
    0.00000000
    ","
    available_waves
    ":"
    0.00000000
    ","
    xcoin_last_waves
    ":"
    3632
    ","
    total_itc
    ":"
    0.000000000000000000
    ","
    in_u
    se_itc
    ":"
    0.00000000
    ","
    available_itc
    ":"
    0.00000000
    ","
    xcoin_last_itc
    ":"
    0
    ","
    total_true
    ":"
    0.000000000000000000
    ","
    in_use_true
    ":"
    0.00000000
    ","
    available_
    true
    ":"
    0.00000000
    ","
    xcoin_last_true
    ":"
    0
    ","
    total_abt
    ":"
    0.000000000000000000
    ","
    in_use_abt
    ":"
    0.00000000
    ","
    available_abt
    ":"
    0.00000000
    ","
    xcoin_last_ab
    t
    ":"
    0
    ","
    total_link
    ":"
    0.000031132075471698
    ","
    in_use_link
    ":"
    0.00000000
    ","
    available_link
    ":"
    0.00003113
    ","
    xcoin_last_link
    ":"
    20420
    ","
    total_meetone
    ":"
    0.
    00000000
    ","
    in_use_meetone
    ":"
    0.00000000
    ","
    available_meetone
    ":"
    0.00000000
    ","
    xcoin_last_meetone
    ":"
    0
    ","
    total_horus
    ":"
    0.00000000
    ","
    in_use_horus
    ":"
    0.00
    000000
    ","
    available_horus
    ":"
    0.00000000
    ","
    xcoin_last_horus
    ":"
    0
    ","
    total_add
    ":"
    0.00000000
    ","
    in_use_add
    ":"
    0.00000000
    ","
    available_add
    ":"
    0.00000000
    ","
    xc
    oin_last_add
    ":"
    0
    ","
    total_salt
    ":"
    0.00000000
    ","
    in_use_salt
    ":"
    0.00000000
    ","
    available_salt
    ":"
    0.00000000
    ","
    xcoin_last_salt
    ":"
    0
    ","
    total_pst
    ":"
    0.0000000
    00000000000
    ","
    in_use_pst
    ":"
    0.00000000
    ","
    available_pst
    ":"
    0.00000000
    ","
    xcoin_last_pst
    ":"
    0
    ","
    total_bhpc
    ":"
    0.000000000000000000
    ","
    in_use_bhpc
    ":"
    0.000
    00000
    ","
    available_bhpc
    ":"
    0.00000000
    ","
    xcoin_last_bhpc
    ":"
    0
    ","
    total_rnt
    ":"
    0.000000000000000000
    ","
    in_use_rnt
    ":"
    0.00000000
    ","
    available_rnt
    ":"
    0.000000
    00
    ","
    xcoin_last_rnt
    ":"
    0
    ","
    total_enj
    ":"
    0.000000000000000000
    ","
    in_use_enj
    ":"
    0.00000000
    ","
    available_enj
    ":"
    0.00000000
    ","
    xcoin_last_enj
    ":"
    517
    ","
    total_
    plx
    ":"
    0.000000000
    ","
    in_use_plx
    ":"
    0.00000000
    ","
    available_plx
    ":"
    0.00000000
    ","
    xcoin_last_plx
    ":"
    0
    ","
    total_vet
    ":"
    0.000000000000000000
    ","
    in_use_vet
    ":"
    0
    .00000000
    ","
    available_vet
    ":"
    0.00000000
    ","
    xcoin_last_vet
    ":"
    46.64
    ","
    total_mtl
    ":"
    0.00000000
    ","
    in_use_mtl
    ":"
    0.00000000
    ","
    available_mtl
    ":"
    0.00000000
    ",
    "xcoin_last_mtl": "2134",
    "total_rdn": "0.000000000000000000",
    "in_use_rdn": "0.00000000",
    "available_rdn": "0.00000000",
    "xcoin_last_rdn": "0",
    "total_ins
    ":"
    0.0000000000
    ","
    in_use_ins
    ":"
    0.00000000
    ","
    available_ins
    ":"
    0.00000000
    ","
    xcoin_last_ins
    ":"
    0
    ","
    total_chl
    ":"
    0.00000000
    ","
    in_use_chl
    ":"
    0.00000000
    ","
    available_chl
    ":"
    0.00000000
    ","
    xcoin_last_chl
    ":"
    0
    ","
    total_black
    ":"
    0.00000000
    ","
    in_use_black
    ":"
    0.00000000
    ","
    available_black
    ":"
    0.00000000
    ","
    xcoin_las
    t_black
    ":"
    0
    ","
    total_atd
    ":"
    0.00000000
    ","
    in_use_atd
    ":"
    0.00000000
    ","
    available_atd
    ":"
    0.00000000
    ","
    xcoin_last_atd
    ":"
    0
    ","
    total_iost
    ":"
    0.00000000
    ","
    in_u
    se_iost
    ":"
    0.00000000
    ","
    available_iost
    ":"
    0.00000000
    ","
    xcoin_last_iost
    ":"
    13.55
    ","
    total_ocn
    ":"
    0.000000000000000000
    ","
    in_use_ocn
    ":"
    0.00000000
    ","
    avail
    able_ocn
    ":"
    0.00000000
    ","
    xcoin_last_ocn
    ":"
    0
    ","
    total_tmtg
    ":"
    0.000048178757269667
    ","
    in_use_tmtg
    ":"
    0.00000000
    ","
    available_tmtg
    ":"
    0.00004817
    ","
    xcoin_l
    ast_tmtg
    ":"
    0
    ","
    total_qkc
    ":"
    0.000000000000000000
    ","
    in_use_qkc
    ":"
    0.00000000
    ","
    available_qkc
    ":"
    0.00000000
    ","
    xcoin_last_qkc
    ":"
    0
    ","
    total_bznt
    ":"
    0.0000
    00000000000000
    ","
    in_use_bznt
    ":"
    0.00000000
    ","
    available_bznt
    ":"
    0.00000000
    ","
    xcoin_last_bznt
    ":"
    0
    ","
    total_arn
    ":"
    0.00000000
    ","
    in_use_arn
    ":"
    0.00000000
    ",
    "available_arn": "0.00000000",
    "xcoin_last_arn": "0",
    "total_atolo": "0.00000000",
    "in_use_atolo": "0.00000000",
    "available_atolo": "0.00000000",
    "xcoin_l
    ast_atolo
    ":"
    0
    ","
    total_npxs
    ":"
    0.000000000000000000
    ","
    in_use_npxs
    ":"
    0.00000000
    ","
    available_npxs
    ":"
    0.00000000
    ","
    xcoin_last_npxs
    ":"
    0
    ","
    total_lba
    ":"
    0.
    000000000000000000
    ","
    in_use_lba
    ":"
    0.00000000
    ","
    available_lba
    ":"
    0.00000000
    ","
    xcoin_last_lba
    ":"
    0
    ","
    total_wet
    ":"
    0.000000000000000000
    ","
    in_use_wet
    ":"
    0.00000000
    ","
    available_wet
    ":"
    0.00000000
    ","
    xcoin_last_wet
    ":"
    0
    ","
    total_amo
    ":"
    0.000001332318233727
    ","
    in_use_amo
    ":"
    0.00000000
    ","
    available_amo
    ":"
    0.000
    00133
    ","
    xcoin_last_amo
    ":"
    0.7971
    ","
    total_bsv
    ":"
    0.00000000
    ","
    in_use_bsv
    ":"
    0.00000000
    ","
    available_bsv
    ":"
    0.00000000
    ","
    xcoin_last_bsv
    ":"
    124000
    ","
    total
    _keos
    ":"
    0.00000000
    ","
    in_use_keos
    ":"
    0.00000000
    ","
    available_keos
    ":"
    0.00000000
    ","
    xcoin_last_keos
    ":"
    0
    ","
    total_rom
    ":"
    0.000000000000000000
    ","
    in_use_rom
    ":"
    0.00000000
    ","
    available_rom
    ":"
    0.00000000
    ","
    xcoin_last_rom
    ":"
    0
    ","
    total_bxa
    ":"
    0.000000000000000000
    ","
    in_use_bxa
    ":"
    0.00000000
    ","
    available_bxa
    ":"
    0.
    00000000
    ","
    xcoin_last_bxa
    ":"
    0
    ","
    total_apis
    ":"
    0.000000000000000000
    ","
    in_use_apis
    ":"
    0.00000000
    ","
    available_apis
    ":"
    0.00000000
    ","
    xcoin_last_apis
    ":"
    0
    ",
    "total_dac": "0.000000000000000000",
    "in_use_dac": "0.00000000",
    "available_dac": "0.00000000",
    "xcoin_last_dac": "0",
    "total_dacc": "0.00000000",
    "in_use
    _dacc
    ":"
    0.00000000
    ","
    available_dacc
    ":"
    0.00000000
    ","
    xcoin_last_dacc
    ":"
    0
    ","
    total_auto
    ":"
    0.000000000000000000
    ","
    in_use_auto
    ":"
    0.00000000
    ","
    available
    _auto
    ":"
    0.00000000
    ","
    xcoin_last_auto
    ":"
    0
    ","
    total_orbs
    ":"
    0.000000000000000000
    ","
    in_use_orbs
    ":"
    0.00000000
    ","
    available_orbs
    ":"
    0.00000000
    ","
    xcoin_las
    t_orbs
    ":"
    53.73
    ","
    total_tfuel
    ":"
    0.000000000000000000
    ","
    in_use_tfuel
    ":"
    0.00000000
    ","
    available_tfuel
    ":"
    0.00000000
    ","
    xcoin_last_tfuel
    ":"
    63.91
    ","
    total
    _valor
    ":"
    0.000000000000000000
    ","
    in_use_valor
    ":"
    0.00000000
    ","
    available_valor
    ":"
    0.00000000
    ","
    xcoin_last_valor
    ":"
    227
    ","
    total_con
    ":"
    0.000000000000000
    000
    ","
    in_use_con
    ":"
    0.00000000
    ","
    available_con
    ":"
    0.00000000
    ","
    xcoin_last_con
    ":"
    6.56
    ","
    total_ankr
    ":"
    0.000000000000000000
    ","
    in_use_ankr
    ":"
    0.00000000
    ","
    available_ankr
    ":"
    0.00000000
    ","
    xcoin_last_ankr
    ":"
    38.74
    ","
    total_mix
    ":"
    0.000088313686053361
    ","
    in_use_mix
    ":"
    0.00000000
    ","
    available_mix
    ":"
    0.0000883
    1
    ","
    xcoin_last_mix
    ":"
    3.845
    ","
    total_vtho
    ":"
    0.000000000000000000
    ","
    in_use_vtho
    ":"
    0.00000000
    ","
    available_vtho
    ":"
    0.00000000
    ","
    xcoin_last_vtho
    ":"
    0
    ","
    t
    otal_lamb
    ":"
    0.000000000000000000
    ","
    in_use_lamb
    ":"
    0.00000000
    ","
    available_lamb
    ":"
    0.00000000
    ","
    xcoin_last_lamb
    ":"
    0
    ","
    total_cro
    ":"
    0.00000000
    ","
    in_use
    _cro
    ":"
    0.00000000
    ","
    available_cro
    ":"
    0.00000000
    ","
    xcoin_last_cro
    ":"
    135
    ","
    total_fx
    ":"
    0.000000000000000000
    ","
    in_use_fx
    ":"
    0.00000000
    ","
    available_fx
    ":
    "0.00000000",
    "xcoin_last_fx": "224",
    "total_chr": "0.00000000",
    "in_use_chr": "0.00000000",
    "available_chr": "0.00000000",
    "xcoin_last_chr": "266",
    "total_
    mbl
    ":"
    0.00000000
    ","
    in_use_mbl
    ":"
    0.00000000
    ","
    available_mbl
    ":"
    0.00000000
    ","
    xcoin_last_mbl
    ":"
    6.469
    ","
    total_mxc
    ":"
    0.000000000000000000
    ","
    in_use_mxc
    ": "0.00000000",
    "available_mxc": "0.00000000",
    "xcoin_last_mxc": "10.47",
    "total_fab": "0.000000000000000000",
    "in_use_fab": "0.00000000",
    "available_fab": "0.00000000",
    "xcoin_last_fab": "0",
    "total_ogo": "0.000000000000000000",
    "in_use_ogo": "0.00000000",
    "available_ogo": "0.00000000",
    "xcoin_last_ogo": "0",
    "total_win": "0.00000000",
    "in_use_win": "0.00000000",
    "available_win": "0.00000000",
    "xcoin_last_win": "0",
    "total_dvp": "0.000000000000000000",
    "in_use_d
    vp
    ":"
    0.00000000
    ","
    available_dvp
    ":"
    0.00000000
    ","
    xcoin_last_dvp
    ":"
    0
    ","
    total_fct2
    ":"
    0.00000000
    ","
    in_use_fct2
    ":"
    0.00000000
    ","
    available_fct2
    ":"
    0.00000
    000
    ","
    xcoin_last_fct2
    ":"
    84.19
    ","
    total_fnb
    ":"
    0.000000000000000000
    ","
    in_use_fnb
    ":"
    0.00000000
    ","
    available_fnb
    ":"
    0.00000000
    ","
    xcoin_last_fnb
    ":"
    0
    ","
    to
    tal_fzz
    ":"
    0.000000000000000000
    ","
    in_use_fzz
    ":"
    0.00000000
    ","
    available_fzz
    ":"
    0.00000000
    ","
    xcoin_last_fzz
    ":"
    0
    ","
    total_trv
    ":"
    0.000015893694632621
    ","
    i
    n_use_trv
    ":"
    0.00000000
    ","
    available_trv
    ":"
    0.00001589
    ","
    xcoin_last_trv
    ":"
    0
    ","
    total_pcm
    ":"
    0.000000000000000000
    ","
    in_use_pcm
    ":"
    0.00000000
    ","
    available
    _pcm
    ":"
    0.00000000
    ","
    xcoin_last_pcm
    ":"
    0
    ","
    total_dad
    ":"
    0.000000000
    ","
    in_use_dad
    ":"
    0.00000000
    ","
    available_dad
    ":"
    0.00000000
    ","
    xcoin_last_dad
    ":"
    0
    ","
    to
    tal_aoa
    ":"
    0.804800000000000000
    ","
    in_use_aoa
    ":"
    0.00000000
    ","
    available_aoa
    ":"
    0.80480000
    ","
    xcoin_last_aoa
    ":"
    0
    ","
    total_xsr
    ":"
    0.457100000000000000
    ","
    i
    n_use_xsr
    ":"
    0.00000000
    ","
    available_xsr
    ":"
    0.45710000
    ","
    xcoin_last_xsr
    ":"
    0
    ","
    total_wom
    ":"
    0.000000000000000000
    ","
    in_use_wom
    ":"
    0.00000000
    ","
    available
    _wom
    ":"
    0.00000000
    ","
    xcoin_last_wom
    ":"
    33.37
    ","
    total_soc
    ":"
    0.000000000000000000
    ","
    in_use_soc
    ":"
    0.00000000
    ","
    available_soc
    ":"
    0.00000000
    ","
    xcoin_last
    _soc
    ":"
    0
    ","
    total_em
    ":"
    0.000000000000000000
    ","
    in_use_em
    ":"
    0.00000000
    ","
    available_em
    ":"
    0.00000000
    ","
    xcoin_last_em
    ":"
    0
    ","
    total_qbz
    ":"
    0.0000000000000
    00000
    ","
    in_use_qbz
    ":"
    0.00000000
    ","
    available_qbz
    ":"
    0.00000000
    ","
    xcoin_last_qbz
    ":"
    0
    ","
    total_boa
    ":"
    0.0000000
    ","
    in_use_boa
    ":"
    0.00000000
    ","
    available_b
    oa
    ":"
    0.00000000
    ","
    xcoin_last_boa
    ":"
    21.8
    ","
    total_wpx
    ":"
    0.000000000000000000
    ","
    in_use_wpx
    ":"
    0.00000000
    ","
    available_wpx
    ":"
    0.00000000
    ","
    xcoin_last_wp
    x
    ":"
    0
    ","
    total_mev
    ":"
    0.474600000000000000
    ","
    in_use_mev
    ":"
    0.00000000
    ","
    available_mev
    ":"
    0.47460000
    ","
    xcoin_last_mev
    ":"
    8.827
    ","
    total_bnp
    ":"
    0.00000000
    0000000000
    ","
    in_use_bnp
    ":"
    0.00000000
    ","
    available_bnp
    ":"
    0.00000000
    ","
    xcoin_last_bnp
    ":"
    0
    ","
    total_sxp
    ":"
    0.00000000
    ","
    in_use_sxp
    ":"
    0.00000000
    ","
    avail
    able_sxp
    ":"
    0.00000000
    ","
    xcoin_last_sxp
    ":"
    541
    ","
    total_cos
    ":"
    0.000000000000000000
    ","
    in_use_cos
    ":"
    0.00000000
    ","
    available_cos
    ":"
    0.00000000
    ","
    xcoin_la
    st_cos
    ":"
    11.74
    ","
    total_apix
    ":"
    0.000000000000000000
    ","
    in_use_apix
    ":"
    0.00000000
    ","
    available_apix
    ":"
    0.00000000
    ","
    xcoin_last_apix
    ":"
    0
    ","
    total_el
    ":"
    0.
    000000000000000000
    ","
    in_use_el
    ":"
    0.00000000
    ","
    available_el
    ":"
    0.00000000
    ","
    xcoin_last_el
    ":"
    3.535
    ","
    total_basic
    ":"
    0.000000000000000000
    ","
    in_use_bas
    ic
    ":"
    0.00000000
    ","
    available_basic
    ":"
    0.00000000
    ","
    xcoin_last_basic
    ":"
    0
    ","
    total_hive
    ":"
    0.00000000
    ","
    in_use_hive
    ":"
    0.00000000
    ","
    available_hive
    ":"
    0.0
    0000000
    ","
    xcoin_last_hive
    ":"
    492
    ","
    total_xpr
    ":"
    0.00000000
    ","
    in_use_xpr
    ":"
    0.00000000
    ","
    available_xpr
    ":"
    0.00000000
    ","
    xcoin_last_xpr
    ":"
    1.399
    ","
    total_
    vra
    ":"
    0.000000000000000000
    ","
    in_use_vra
    ":"
    0.00000000
    ","
    available_vra
    ":"
    0.00000000
    ","
    xcoin_last_vra
    ":"
    9.512
    ","
    total_fit
    ":"
    0.000093461655973114
    ","
    i
    n_use_fit
    ":"
    0.00000000
    ","
    available_fit
    ":"
    0.00009346
    ","
    xcoin_last_fit
    ":"
    0.6896
    ","
    total_egg
    ":"
    0.000000000000000000
    ","
    in_use_egg
    ":"
    0.00000000
    ","
    avai
    lable_egg
    ":"
    0.00000000
    ","
    xcoin_last_egg
    ":"
    5.405
    ","
    total_bora
    ":"
    0.000000000000000000
    ","
    in_use_bora
    ":"
    0.00000000
    ","
    available_bora
    ":"
    0.00000000
    ","
    xc
    oin_last_bora
    ":"
    209
    ","
    total_arpa
    ":"
    0.000000000000000000
    ","
    in_use_arpa
    ":"
    0.00000000
    ","
    available_arpa
    ":"
    0.00000000
    ","
    xcoin_last_arpa
    ":"
    73.84
    ","
    tota
    l_ctc
    ":"
    0.000000000000000000
    ","
    in_use_ctc
    ":"
    0.00000000
    ","
    available_ctc
    ":"
    0.00000000
    ","
    xcoin_last_ctc
    ":"
    896
    ","
    total_apm
    ":"
    0.000000000000000000
    ","
    i
    n_use_apm
    ":"
    0.00000000
    ","
    available_apm
    ":"
    0.00000000
    ","
    xcoin_last_apm
    ":"
    10.19
    ","
    total_ckb
    ":"
    0.00000000
    ","
    in_use_ckb
    ":"
    0.00000000
    ","
    available_ckb
    ":
    "0.00000000",
    "xcoin_last_ckb": "5.246",
    "total_aergo": "0.000000000000000000",
    "in_use_aergo": "0.00000000",
    "available_aergo": "0.00000000",
    "xcoin_last
    _aergo
    ":"
    200
    ","
    total_anw
    ":"
    0.000000000000000000
    ","
    in_use_anw
    ":"
    0.00000000
    ","
    available_anw
    ":"
    0.00000000
    ","
    xcoin_last_anw
    ":"
    0
    ","
    total_cennz
    ":"
    0.000
    000000000000000
    ","
    in_use_cennz
    ":"
    0.00000000
    ","
    available_cennz
    ":"
    0.00000000
    ","
    xcoin_last_cennz
    ":"
    0
    ","
    total_evz
    ":"
    0.000000000000000000
    ","
    in_use_evz
    ":"
    0.00000000
    ","
    available_evz
    ":"
    0.00000000
    ","
    xcoin_last_evz
    ":"
    10.62
    ","
    total_cyclub
    ":"
    0.000000000
    ","
    in_use_cyclub
    ":"
    0.00000000
    ","
    available_cyclub
    ": "0.00000000",
    "xcoin_last_cyclub": "0",
    "total_srm": "0.00000000",
    "in_use_srm": "0.00000000",
    "available_srm": "0.00000000",
    "xcoin_last_srm": "0",
    "total
    _qtcon
    ":"
    0.000092515723270440
    ","
    in_use_qtcon
    ":"
    0.00000000
    ","
    available_qtcon
    ":"
    0.00009251
    ","
    xcoin_last_qtcon
    ":"
    2.26
    ","
    total_uni
    ":"
    0.00000000000000
    0000
    ","
    in_use_uni
    ":"
    0.00000000
    ","
    available_uni
    ":"
    0.00000000
    ","
    xcoin_last_uni
    ":"
    10000
    ","
    total_yfi
    ":"
    0.000000000000000000
    ","
    in_use_yfi
    ":"
    0.00000000
    ","
    available_yfi
    ":"
    0.00000000
    ","
    xcoin_last_yfi
    ":"
    11033000
    ","
    total_uma
    ":"
    0.000000000000000000
    ","
    in_use_uma
    ":"
    0.00000000
    ","
    available_uma
    ":"
    0.000000
    00
    ","
    xcoin_last_uma
    ":"
    3040
    ","
    total_aave
    ":"
    0.000000000000000000
    ","
    in_use_aave
    ":"
    0.00000000
    ","
    available_aave
    ":"
    0.00000000
    ","
    xcoin_last_aave
    ":"
    14990
    0
    ","
    total_comp
    ":"
    0.000000000000000000
    ","
    in_use_comp
    ":"
    0.00000000
    ","
    available_comp
    ":"
    0.00000000
    ","
    xcoin_last_comp
    ":"
    78700
    ","
    total_ren
    ":"
    0.00000000
    0000000000
    ","
    in_use_ren
    ":"
    0.00000000
    ","
    available_ren
    ":"
    0.00000000
    ","
    xcoin_last_ren
    ":"
    0
    ","
    total_bal
    ":"
    0.000000000000000000
    ","
    in_use_bal
    ":"
    0.000000
    00
    ","
    available_bal
    ":"
    0.00000000
    ","
    xcoin_last_bal
    ":"
    5760
    ","
    total_rsr
    ":"
    0.000000000000000000
    ","
    in_use_rsr
    ":"
    0.00000000
    ","
    available_rsr
    ":"
    0.00000000
    ","
    xcoin_last_rsr
    ":"
    4.404
    ","
    total_nmr
    ":"
    0.000000000000000000
    ","
    in_use_nmr
    ":"
    0.00000000
    ","
    available_nmr
    ":"
    0.00000000
    ","
    xcoin_last_nmr
    ":"
    28160
    ","
    to
    tal_rlc
    ":"
    0.000000000
    ","
    in_use_rlc
    ":"
    0.00000000
    ","
    available_rlc
    ":"
    0.00000000
    ","
    xcoin_last_rlc
    ":"
    2360
    ","
    total_uos
    ":"
    0.00000000
    ","
    in_use_uos
    ":"
    0.00
    000000
    ","
    available_uos
    ":"
    0.00000000
    ","
    xcoin_last_uos
    ":"
    287
    ","
    total_sand
    ":"
    0.000000000000000000
    ","
    in_use_sand
    ":"
    0.00000000
    ","
    available_sand
    ":"
    0.00
    000000
    ","
    xcoin_last_sand
    ":"
    800
    ","
    total_cvt
    ":"
    0.000000000000000000
    ","
    in_use_cvt
    ":"
    0.00000000
    ","
    available_cvt
    ":"
    0.00000000
    ","
    xcoin_last_cvt
    ":"
    0
    ","
    t
    otal_stpt
    ":"
    0.000000000000000000
    ","
    in_use_stpt
    ":"
    0.00000000
    ","
    available_stpt
    ":"
    0.00000000
    ","
    xcoin_last_stpt
    ":"
    83.57
    ","
    total_gom2
    ":"
    0.000000000000
    000000
    ","
    in_use_gom2
    ":"
    0.00000000
    ","
    available_gom2
    ":"
    0.00000000
    ","
    xcoin_last_gom2
    ":"
    0
    ","
    total_ringx
    ":"
    0.000000000000000000
    ","
    in_use_ringx
    ":"
    0.000
    00000
    ","
    available_ringx
    ":"
    0.00000000
    ","
    xcoin_last_ringx
    ":"
    0
    ","
    total_bel
    ":"
    0.000000000000000000
    ","
    in_use_bel
    ":"
    0.00000000
    ","
    available_bel
    ":"
    0.0000
    0000
    ","
    xcoin_last_bel
    ":"
    972
    ","
    total_dvc
    ":"
    0.000000000000000000
    ","
    in_use_dvc
    ":"
    0.00000000
    ","
    available_dvc
    ":"
    0.00000000
    ","
    xcoin_last_dvc
    ":"
    0
    ","
    tota
    l_obsr
    ":"
    0.00000000
    ","
    in_use_obsr
    ":"
    0.00000000
    ","
    available_obsr
    ":"
    0.00000000
    ","
    xcoin_last_obsr
    ":"
    2.268
    ","
    total_orc
    ":"
    0.000000000000000000
    ","
    in_us
    e_orc
    ":"
    0.00000000
    ","
    available_orc
    ":"
    0.00000000
    ","
    xcoin_last_orc
    ":"
    94.17
    ","
    total_pola
    ":"
    0.000000000000000000
    ","
    in_use_pola
    ":"
    0.00000000
    ","
    availab
    le_pola
    ":"
    0.00000000
    ","
    xcoin_last_pola
    ":"
    19.16
    ","
    total_awo
    ":"
    0.000000000000000000
    ","
    in_use_awo
    ":"
    0.00000000
    ","
    available_awo
    ":"
    0.00000000
    ","
    xcoin_
    last_awo
    ":"
    0
    ","
    total_adp
    ":"
    0.000054400785608990
    ","
    in_use_adp
    ":"
    0.00000000
    ","
    available_adp
    ":"
    0.00005440
    ","
    xcoin_last_adp
    ":"
    3.052
    ","
    total_dvi
    ":"
    0.0
    00000000000000000
    ","
    in_use_dvi
    ":"
    0.00000000
    ","
    available_dvi
    ":"
    0.00000000
    ","
    xcoin_last_dvi
    ":"
    20.16
    ","
    total_drm
    ":"
    0.000000000000000000
    ","
    in_use_drm
    ":"
    0.00000000
    ","
    available_drm
    ":"
    0.00000000
    ","
    xcoin_last_drm
    ":"
    0
    ","
    total_ibp
    ":"
    0.000000000000000000
    ","
    in_use_ibp
    ":"
    0.00000000
    ","
    available_ibp
    ":"
    0.
    00000000
    ","
    xcoin_last_ibp
    ":"
    0
    ","
    total_ghx
    ":"
    0.000000000000000000
    ","
    in_use_ghx
    ":"
    0.00000000
    ","
    available_ghx
    ":"
    0.00000000
    ","
    xcoin_last_ghx
    ":"
    15.65
    ",
    "total_mir": "0.000000000000000000",
    "in_use_mir": "0.00000000",
    "available_mir": "0.00000000",
    "xcoin_last_mir": "0",
    "total_cbk": "0.000000000000000000
    ","
    in_use_cbk
    ":"
    0.00000000
    ","
    available_cbk
    ":"
    0.00000000
    ","
    xcoin_last_cbk
    ":"
    0
    ","
    total_onx
    ":"
    0.000000000000000000
    ","
    in_use_onx
    ":"
    0.00000000
    ","
    avail
    able_onx
    ":"
    0.00000000
    ","
    xcoin_last_onx
    ":"
    0
    ","
    total_mvc
    ":"
    0.000000000000000000
    ","
    in_use_mvc
    ":"
    0.00000000
    ","
    available_mvc
    ":"
    0.00000000
    ","
    xcoin_last
    _mvc
    ":"
    2.997
    ","
    total_bly
    ":"
    0.000000000000000000
    ","
    in_use_bly
    ":"
    0.00000000
    ","
    available_bly
    ":"
    0.00000000
    ","
    xcoin_last_bly
    ":"
    6.683
    ","
    total_wozx
    ":"
    0.
    000000000000000000
    ","
    in_use_wozx
    ":"
    0.00000000
    ","
    available_wozx
    ":"
    0.00000000
    ","
    xcoin_last_wozx
    ":"
    0
    ","
    total_anv
    ":"
    0.000071975180972078
    ","
    in_use_anv
    ":"
    0.00000000
    ","
    available_anv
    ":"
    0.00007197
    ","
    xcoin_last_anv
    ":"
    25.93
    ","
    total_grt
    ":"
    0.000000000000000000
    ","
    in_use_grt
    ":"
    0.00000000
    ","
    available_grt
    ": "0.00000000",
    "xcoin_last_grt": "251",
    "total_mm": "0.000000000000000000",
    "in_use_mm": "0.00000000",
    "available_mm": "0.00000000",
    "xcoin_last_mm": "0",
    "
    total_biot
    ":"
    0.000000000
    ","
    in_use_biot
    ":"
    0.00000000
    ","
    available_biot
    ":"
    0.00000000
    ","
    xcoin_last_biot
    ":"
    1.495
    ","
    total_xno
    ":"
    0.000000000000000000
    ","
    in_use_xno
    ":"
    0.00000000
    ","
    available_xno
    ":"
    0.00000000
    ","
    xcoin_last_xno
    ":"
    0
    ","
    total_snx
    ":"
    0.000000000000000000
    ","
    in_use_snx
    ":"
    0.00000000
    ","
    availabl
    e_snx
    ":"
    0.00000000
    ","
    xcoin_last_snx
    ":"
    5315
    ","
    total_sofi
    ":"
    0.000000000000000000
    ","
    in_use_sofi
    ":"
    0.00000000
    ","
    available_sofi
    ":"
    0.00000000
    ","
    xcoin_l
    ast_sofi
    ":"
    41.6
    ","
    total_gracy
    ":"
    0.000000000000000000
    ","
    in_use_gracy
    ":"
    0.00000000
    ","
    available_gracy
    ":"
    0.00000000
    ","
    xcoin_last_gracy
    ":"
    55.04
    ","
    tota
    l_nu
    ":"
    0.000000000000000000
    ","
    in_use_nu
    ":"
    0.00000000
    ","
    available_nu
    ":"
    0.00000000
    ","
    xcoin_last_nu
    ":"
    0
    ","
    total_oxt
    ":"
    0.000000000000000000
    ","
    in_use_
    oxt
    ":"
    0.00000000
    ","
    available_oxt
    ":"
    0.00000000
    ","
    xcoin_last_oxt
    ":"
    149
    ","
    total_lina
    ":"
    0.000000000000000000
    ","
    in_use_lina
    ":"
    0.00000000
    ","
    available_l
    ina
    ":"
    0.00000000
    ","
    xcoin_last_lina
    ":"
    0
    ","
    total_asta
    ":"
    0.000000000000000000
    ","
    in_use_asta
    ":"
    0.00000000
    ","
    available_asta
    ":"
    0.00000000
    ","
    xcoin_last_
    asta
    ":"
    0
    ","
    total_map
    ":"
    0.000000000000000000
    ","
    in_use_map
    ":"
    0.00000000
    ","
    available_map
    ":"
    0.00000000
    ","
    xcoin_last_map
    ":"
    42.98
    ","
    total_aqt
    ":"
    0.00000
    0000000000000
    ","
    in_use_aqt
    ":"
    0.00000000
    ","
    available_aqt
    ":"
    0.00000000
    ","
    xcoin_last_aqt
    ":"
    1927
    ","
    total_pla
    ":"
    0.000000000000000000
    ","
    in_use_pla
    ":"
    0.
    00000000
    ","
    available_pla
    ":"
    0.00000000
    ","
    xcoin_last_pla
    ":"
    289
    ","
    total_wiken
    ":"
    0.000000000000000000
    ","
    in_use_wiken
    ":"
    0.00000000
    ","
    available_wiken
    ":
    "0.00000000",
    "xcoin_last_wiken": "11.78",
    "total_ctsi": "0.000000000000000000",
    "in_use_ctsi": "0.00000000",
    "available_ctsi": "0.00000000",
    "xcoin_last_
    ctsi
    ":"
    289
    ","
    total_mana
    ":"
    0.000000000000000000
    ","
    in_use_mana
    ":"
    0.00000000
    ","
    available_mana
    ":"
    0.00000000
    ","
    xcoin_last_mana
    ":"
    705
    ","
    total_lpt
    ":"
    0.0
    00000000000000000
    ","
    in_use_lpt
    ":"
    0.00000000
    ","
    available_lpt
    ":"
    0.00000000
    ","
    xcoin_last_lpt
    ":"
    10860
    ","
    total_mkr
    ":"
    0.000000000000000000
    ","
    in_use_mkr
    ":"
    0.00000000
    ","
    available_mkr
    ":"
    0.00000000
    ","
    xcoin_last_mkr
    ":"
    2326000
    ","
    total_srt
    ":"
    0.000000000000000000
    ","
    in_use_srt
    ":"
    0.00000000
    ","
    available_sr
    t
    ":"
    0.00000000
    ","
    xcoin_last_srt
    ":"
    0
    ","
    total_sushi
    ":"
    0.000000000000000000
    ","
    in_use_sushi
    ":"
    0.00000000
    ","
    available_sushi
    ":"
    0.00000000
    ","
    xcoin_last_
    sushi
    ":"
    1727
    ","
    total_nsbt
    ":"
    0.00000000
    ","
    in_use_nsbt
    ":"
    0.00000000
    ","
    available_nsbt
    ":"
    0.00000000
    ","
    xcoin_last_nsbt
    ":"
    0
    ","
    total_don
    ":"
    0.00000000
    ","
    in_use_don
    ":"
    0.00000000
    ","
    available_don
    ":"
    0.00000000
    ","
    xcoin_last_don
    ":"
    0
    ","
    total_asm
    ":"
    0.000000000000000000
    ","
    in_use_asm
    ":"
    0.00000000
    ","
    availabl
    e_asm
    ":"
    0.00000000
    ","
    xcoin_last_asm
    ":"
    76.16
    ","
    total_pundix
    ":"
    0.000000000000000000
    ","
    in_use_pundix
    ":"
    0.00000000
    ","
    available_pundix
    ":"
    0.00000000
    ","
    xcoin_last_pundix
    ":"
    651
    ","
    total_celr
    ":"
    0.000000000000000000
    ","
    in_use_celr
    ":"
    0.00000000
    ","
    available_celr
    ":"
    0.00000000
    ","
    xcoin_last_celr
    ":"
    29.66
    ","
    total_cwd
    ":"
    0.000000000000000000
    ","
    in_use_cwd
    ":"
    0.00000000
    ","
    available_cwd
    ":"
    0.00000000
    ","
    xcoin_last_cwd
    ":"
    0
    ","
    total_arw
    ":"
    0.000078285923813938
    ",
    "in_use_arw": "0.00000000",
    "available_arw": "0.00007828",
    "xcoin_last_arw": "0",
    "total_beth": "0.000000000000000000",
    "in_use_beth": "0.00000000",
    "avail
    able_beth
    ":"
    0.00000000
    ","
    xcoin_last_beth
    ":"
    0
    ","
    total_bcdc
    ":"
    0.000000000000000000
    ","
    in_use_bcdc
    ":"
    0.00000000
    ","
    available_bcdc
    ":"
    0.00000000
    ","
    xcoin
    _last_bcdc
    ":"
    0
    ","
    total_front
    ":"
    0.000000000000000000
    ","
    in_use_front
    ":"
    0.00000000
    ","
    available_front
    ":"
    0.00000000
    ","
    xcoin_last_front
    ":"
    567
    ","
    total_m
    sb
    ":"
    0.000000000000000000
    ","
    in_use_msb
    ":"
    0.00000000
    ","
    available_msb
    ":"
    0.00000000
    ","
    xcoin_last_msb
    ":"
    0
    ","
    total_rly
    ":"
    0.000000000000000000
    ","
    in_use
    _rly
    ":"
    0.00000000
    ","
    available_rly
    ":"
    0.00000000
    ","
    xcoin_last_rly
    ":"
    10.96
    ","
    total_ocean
    ":"
    0.000000000000000000
    ","
    in_use_ocean
    ":"
    0.00000000
    ","
    availa
    ble_ocean
    ":"
    0.00000000
    ","
    xcoin_last_ocean
    ":"
    697
    ","
    total_bfc
    ":"
    0.000030641703385364
    ","
    in_use_bfc
    ":"
    0.00000000
    ","
    available_bfc
    ":"
    0.00003064
    ","
    xcoin
    _last_bfc
    ":"
    90.22
    ","
    total_alice
    ":"
    0.00000000
    ","
    in_use_alice
    ":"
    0.00000000
    ","
    available_alice
    ":"
    0.00000000
    ","
    xcoin_last_alice
    ":"
    1918
    ","
    total_ogn
    ":"
    0
    .000000000000000000
    ","
    in_use_ogn
    ":"
    0.00000000
    ","
    available_ogn
    ":"
    0.00000000
    ","
    xcoin_last_ogn
    ":"
    195
    ","
    total_coti
    ":"
    0.000000000000000000
    ","
    in_use_co
    ti
    ":"
    0.00000000
    ","
    available_coti
    ":"
    0.00000000
    ","
    xcoin_last_coti
    ":"
    95.02
    ","
    total_cake
    ":"
    0.000000000000000000
    ","
    in_use_cake
    ":"
    0.00000000
    ","
    availabl
    e_cake
    ":"
    0.00000000
    ","
    xcoin_last_cake
    ":"
    4808
    ","
    total_bnt
    ":"
    0.000000000000000000
    ","
    in_use_bnt
    ":"
    0.00000000
    ","
    available_bnt
    ":"
    0.00000000
    ","
    xcoin_la
    st_bnt
    ":"
    1002
    ","
    total_xvs
    ":"
    0.000000000000000000
    ","
    in_use_xvs
    ":"
    0.00000000
    ","
    available_xvs
    ":"
    0.00000000
    ","
    xcoin_last_xvs
    ":"
    15530
    ","
    total_swap
    ":"
    0
    .000000000000000000
    ","
    in_use_swap
    ":"
    0.00000000
    ","
    available_swap
    ":"
    0.00000000
    ","
    xcoin_last_swap
    ":"
    298
    ","
    total_chz
    ":"
    0.000000000000000000
    ","
    in_use_
    chz
    ":"
    0.00000000
    ","
    available_chz
    ":"
    0.00000000
    ","
    xcoin_last_chz
    ":"
    119
    ","
    total_axs
    ":"
    165.482800000000000000
    ","
    in_use_axs
    ":"
    0.00000000
    ","
    available_a
    xs
    ":"
    165.48280000
    ","
    xcoin_last_axs
    ":"
    12230
    ","
    total_dao
    ":"
    0.000000000000000000
    ","
    in_use_dao
    ":"
    0.00000000
    ","
    available_dao
    ":"
    0.00000000
    ","
    xcoin_last
    _dao
    ":"
    1624
    ","
    total_six
    ":"
    0.000000000000000000
    ","
    in_use_six
    ":"
    0.00000000
    ","
    available_six
    ":"
    0.00000000
    ","
    xcoin_last_six
    ":"
    47.51
    ","
    total_dai
    ":"
    0.00
    0000000000000000
    ","
    in_use_dai
    ":"
    0.00000000
    ","
    available_dai
    ":"
    0.00000000
    ","
    xcoin_last_dai
    ":"
    1345
    ","
    total_shib
    ":"
    0.000000000000000000
    ","
    in_use_shib
    ":"
    0.00000000
    ","
    available_shib
    ":"
    0.00000000
    ","
    xcoin_last_shib
    ":"
    0.014
    ","
    total_matic
    ":"
    0.000000000000000000
    ","
    in_use_matic
    ":"
    0.00000000
    ","
    availabl
    e_matic
    ":"
    0.00000000
    ","
    xcoin_last_matic
    ":"
    1325
    ","
    total_woo
    ":"
    0.000000000000000000
    ","
    in_use_woo
    ":"
    0.00000000
    ","
    available_woo
    ":"
    0.00000000
    ","
    xcoin_
    last_woo
    ":"
    539
    ","
    total_ach
    ":"
    0.00000000
    ","
    in_use_ach
    ":"
    0.00000000
    ","
    available_ach
    ":"
    0.00000000
    ","
    xcoin_last_ach
    ":"
    29.12
    ","
    total_bake
    ":"
    0.00000000
    0000000000
    ","
    in_use_bake
    ":"
    0.00000000
    ","
    available_bake
    ":"
    0.00000000
    ","
    xcoin_last_bake
    ":"
    0
    ","
    total_velo
    ":"
    0.000099470967303070
    ","
    in_use_velo
    ":"
    0.0
    0000000
    ","
    available_velo
    ":"
    0.00009947
    ","
    xcoin_last_velo
    ":"
    5.374
    ","
    total_anc
    ":"
    0.000000000000000000
    ","
    in_use_anc
    ":"
    0.00000000
    ","
    available_anc
    ":"
    0.
    00000000
    ","
    xcoin_last_anc
    ":"
    0
    ","
    total_hc
    ":"
    0.00000000
    ","
    in_use_hc
    ":"
    0.00000000
    ","
    available_hc
    ":"
    0.00000000
    ","
    xcoin_last_hc
    ":"
    0
    ","
    total_bcd
    ":"
    0.00
    000000
    ","
    in_use_bcd
    ":"
    0.00000000
    ","
    available_bcd
    ":"
    0.00000000
    ","
    xcoin_last_bcd
    ":"
    0
    ","
    total_xvg
    ":"
    0.00000000
    ","
    in_use_xvg
    ":"
    0.00000000
    ","
    available
    _xvg
    ":"
    0.00000000
    ","
    xcoin_last_xvg
    ":"
    0
    ","
    total_xlm
    ":"
    0.00000000
    ","
    in_use_xlm
    ":"
    0.00000000
    ","
    available_xlm
    ":"
    0.00000000
    ","
    xcoin_last_xlm
    ":"
    174
    ","
    t
    otal_pivx
    ":"
    0.00000000
    ","
    in_use_pivx
    ":"
    0.00000000
    ","
    available_pivx
    ":"
    0.00000000
    ","
    xcoin_last_pivx
    ":"
    0
    ","
    total_etz
    ":"
    0.000000000000000000
    ","
    in_use
    _etz
    ":"
    0.00000000
    ","
    available_etz
    ":"
    0.00000000
    ","
    xcoin_last_etz
    ":"
    0
    ","
    total_gxc
    ":"
    0.00000000
    ","
    in_use_gxc
    ":"
    0.00000000
    ","
    available_gxc
    ":"
    0.000000
    00
    ","
    xcoin_last_gxc
    ":"
    0
    ","
    total_bhp
    ":"
    0.00000000
    ","
    in_use_bhp
    ":"
    0.00000000
    ","
    available_bhp
    ":"
    0.00000000
    ","
    xcoin_last_bhp
    ":"
    0
    ","
    total_bttold
    ":"
    0.0
    0000000
    ","
    in_use_bttold
    ":"
    0.00000000
    ","
    available_bttold
    ":"
    0.00000000
    ","
    xcoin_last_bttold
    ":"
    0
    ","
    total_hyc
    ":"
    0.000000000
    ","
    in_use_hyc
    ":"
    0.00000000
    ",
    "available_hyc": "0.00000000",
    "xcoin_last_hyc": "0",
    "total_vsys": "0.00000000",
    "in_use_vsys": "0.00000000",
    "available_vsys": "0.00000000",
    "xcoin_last
    _vsys
    ":"
    0
    ","
    total_ipx
    ":"
    0.000000000
    ","
    in_use_ipx
    ":"
    0.00000000
    ","
    available_ipx
    ":"
    0.00000000
    ","
    xcoin_last_ipx
    ":"
    0
    ","
    total_wicc
    ":"
    0.00000000
    ","
    in_us
    e_wicc
    ":"
    0.00000000
    ","
    available_wicc
    ":"
    0.00000000
    ","
    xcoin_last_wicc
    ":"
    0
    ","
    total_ont
    ":"
    0.000000000
    ","
    in_use_ont
    ":"
    0.00000000
    ","
    available_ont
    ":"
    0.0
    0000000
    ","
    xcoin_last_ont
    ":"
    437
    ","
    total_lunc
    ":"
    0.00000000
    ","
    in_use_lunc
    ":"
    0.00000000
    ","
    available_lunc
    ":"
    0.00000000
    ","
    xcoin_last_lunc
    ":"
    0
    ","
    total_n
    ews2
    ":"
    0.00000000
    ","
    in_use_news2
    ":"
    0.00000000
    ","
    available_news2
    ":"
    0.00000000
    ","
    xcoin_last_news2
    ":"
    0
    ","
    total_aion
    ":"
    0.000000000000000000
    ","
    in_use_
    aion
    ":"
    0.00000000
    ","
    available_aion
    ":"
    0.00000000
    ","
    xcoin_last_aion
    ":"
    0
    ","
    total_meta
    ":"
    0.000000000000000000
    ","
    in_use_meta
    ":"
    0.00000000
    ","
    available_
    meta
    ":"
    0.00000000
    ","
    xcoin_last_meta
    ":"
    54.46
    ","
    total_klay
    ":"
    0.000000006666384419
    ","
    in_use_klay
    ":"
    0.00000000
    ","
    available_klay
    ":"
    0.00000000
    ","
    xcoin_
    last_klay
    ":"
    311
    ","
    total_cosm
    ":"
    0.000000000000000000
    ","
    in_use_cosm
    ":"
    0.00000000
    ","
    available_cosm
    ":"
    0.00000000
    ","
    xcoin_last_cosm
    ":"
    0
    ","
    total_ong
    ":"
    0.000000000000000000
    ","
    in_use_ong
    ":"
    0.00000000
    ","
    available_ong
    ":"
    0.00000000
    ","
    xcoin_last_ong
    ":"
    528
    ","
    total_algo
    ":"
    0.000000
    ","
    in_use_algo
    ":"
    0.0000
    0000
    ","
    available_algo
    ":"
    0.00000000
    ","
    xcoin_last_algo
    ":"
    307
    ","
    total_jst
    ":"
    0.000000000000000000
    ","
    in_use_jst
    ":"
    0.00000000
    ","
    available_jst
    ":"
    0.00000
    000
    ","
    xcoin_last_jst
    ":"
    43.08
    ","
    total_xtz
    ":"
    0.000000
    ","
    in_use_xtz
    ":"
    0.00000000
    ","
    available_xtz
    ":"
    0.00000000
    ","
    xcoin_last_xtz
    ":"
    1372
    ","
    total_itg
    ":"
    0.000000000000000000
    ","
    in_use_itg
    ":"
    0.00000000
    ","
    available_itg
    ":"
    0.00000000
    ","
    xcoin_last_itg
    ":"
    0
    ","
    total_luk
    ":"
    0.000000000000000000
    ","
    in_use_luk
    ": "0.00000000",
    "available_luk": "0.00000000",
    "xcoin_last_luk": "0",
    "total_mlk": "0.00000000",
    "in_use_mlk": "0.00000000",
    "available_mlk": "0.00000000",
    "
    xcoin_last_mlk
    ":"
    482
    ","
    total_wemixc
    ":"
    0.000000000000000000
    ","
    in_use_wemixc
    ":"
    0.00000000
    ","
    available_wemixc
    ":"
    0.00000000
    ","
    xcoin_last_wemixc
    ":"
    0
    ",
    "total_dot": "0.0000000000",
    "in_use_dot": "0.00000000",
    "available_dot": "0.00000000",
    "xcoin_last_dot": "11180",
    "total_sun_old": "0.000000000000000000",
    "in_use_sun_old": "0.00000000",
    "available_sun_old": "0.00000000",
    "xcoin_last_sun_old": "0",
    "total_atom": "0.00000000",
    "in_use_atom": "0.00000000",
    "av
    ailable_atom
    ":"
    0.00000000
    ","
    xcoin_last_atom
    ":"
    14490
    ","
    total_ssx
    ":"
    0.000000000000000000
    ","
    in_use_ssx
    ":"
    0.00000000
    ","
    available_ssx
    ":"
    0.00000000
    ","
    x
    coin_last_ssx
    ":"
    27.44
    ","
    total_bcha
    ":"
    0.00000000
    ","
    in_use_bcha
    ":"
    0.00000000
    ","
    available_bcha
    ":"
    0.00000000
    ","
    xcoin_last_bcha
    ":"
    0
    ","
    total_temco
    ":"
    0.
    000000000000000000
    ","
    in_use_temco
    ":"
    0.00000000
    ","
    available_temco
    ":"
    0.00000000
    ","
    xcoin_last_temco
    ":"
    2.617
    ","
    total_ksp
    ":"
    0.000000000000000000
    ","
    in_
    use_ksp
    ":"
    0.00000000
    ","
    available_ksp
    ":"
    0.00000000
    ","
    xcoin_last_ksp
    ":"
    0.00001401
    ","
    total_lzm
    ":"
    0.00000000
    ","
    in_use_lzm
    ":"
    0.00000000
    ","
    available_lz
    m
    ":"
    0.00000000
    ","
    xcoin_last_lzm
    ":"
    0
    ","
    total_hibs
    ":"
    0.000000000000000000
    ","
    in_use_hibs
    ":"
    0.00000000
    ","
    available_hibs
    ":"
    0.00000000
    ","
    xcoin_last_hib
    s
    ":"
    0
    ","
    total_cpay
    ":"
    0.00000000
    ","
    in_use_cpay
    ":"
    0.00000000
    ","
    available_cpay
    ":"
    0.00000000
    ","
    xcoin_last_cpay
    ":"
    0
    ","
    total_qi
    ":"
    0.000000000000000000
    ",
    "in_use_qi": "0.00000000",
    "available_qi": "0.00000000",
    "xcoin_last_qi": "0",
    "total_bsc_bnb": "0.000000000000000000",
    "in_use_bsc_bnb": "0.00000000",
    "a
    vailable_bsc_bnb
    ":"
    0.00000000
    ","
    xcoin_last_bsc_bnb
    ":"
    0
    ","
    total_burger
    ":"
    0.000088861438548168
    ","
    in_use_burger
    ":"
    0.00000000
    ","
    available_burger
    ":"
    0.
    00008886
    ","
    xcoin_last_burger
    ":"
    0
    ","
    total_doge
    ":"
    0.00000664
    ","
    in_use_doge
    ":"
    0.00000000
    ","
    available_doge
    ":"
    0.00000664
    ","
    xcoin_last_doge
    ":"
    121
    ","
    tot
    al_ksm
    ":"
    0.000000000000
    ","
    in_use_ksm
    ":"
    0.00000000
    ","
    available_ksm
    ":"
    0.00000000
    ","
    xcoin_last_ksm
    ":"
    62000
    ","
    total_ctk
    ":"
    0.00000000
    ","
    in_use_ctk
    ":"
    0
    .00000000
    ","
    available_ctk
    ":"
    0.00000000
    ","
    xcoin_last_ctk
    ":"
    1056
    ","
    total_xym
    ":"
    0.00000000
    ","
    in_use_xym
    ":"
    0.00000000
    ","
    available_xym
    ":"
    0.00000000
    ","
    xcoin_last_xym
    ":"
    0
    ","
    total_bnb
    ":"
    0.00000000
    ","
    in_use_bnb
    ":"
    0.00000000
    ","
    available_bnb
    ":"
    0.00000000
    ","
    xcoin_last_bnb
    ":"
    422700
    ","
    total_nft
    ":"
    128322
    .15500600
    ","
    in_use_nft
    ":"
    0.00000000
    ","
    available_nft
    ":"
    128322.15500600
    ","
    xcoin_last_nft
    ":"
    0.0006
    ","
    total_sun
    ":"
    0.000000000000000000
    ","
    in_use_sun
    ":
    "0.00000000",
    "available_sun": "0.00000000",
    "xcoin_last_sun": "11.28",
    "total_xec": "0.00000001",
    "in_use_xec": "0.00000000",
    "available_xec": "0.00000001
    ","
    xcoin_last_xec
    ":"
    0.0506
    ","
    total_agix
    ":"
    0.00000000
    ","
    in_use_agix
    ":"
    0.00000000
    ","
    available_agix
    ":"
    0.00000000
    ","
    xcoin_last_agix
    ":"
    439
    ","
    total_pci
    ":"
    0.00000000
    ","
    in_use_pci
    ":"
    0.00000000
    ","
    available_pci
    ":"
    0.00000000
    ","
    xcoin_last_pci
    ":"
    0
    ","
    total_sol
    ":"
    0.000000000
    ","
    in_use_sol
    ":"
    0.00000000
    ","
    a
    vailable_sol
    ":"
    0.00000000
    ","
    xcoin_last_sol
    ":"
    138300
    ","
    total_fnsa
    ":"
    0.00000000
    ","
    in_use_fnsa
    ":"
    0.00000000
    ","
    available_fnsa
    ":"
    0.00000000
    ","
    xcoin_la
    st_fnsa
    ":"
    42070
    ","
    total_egld
    ":"
    0.000000000000000000
    ","
    in_use_egld
    ":"
    0.00000000
    ","
    available_egld
    ":"
    0.00000000
    ","
    xcoin_last_egld
    ":"
    93350
    ","
    total_go
    ":"
    0.000000000000000000
    ","
    in_use_go
    ":"
    0.00000000
    ","
    available_go
    ":"
    0.00000000
    ","
    xcoin_last_go
    ":"
    0
    ","
    total_mask
    ":"
    0.000000000000000000
    ","
    in_use_mas
    k
    ":"
    0.00000000
    ","
    available_mask
    ":"
    0.00000000
    ","
    xcoin_last_mask
    ":"
    4891
    ","
    total_dfa
    ":"
    0.000000000000000000
    ","
    in_use_dfa
    ":"
    0.00000000
    ","
    available_df
    a
    ":"
    0.00000000
    ","
    xcoin_last_dfa
    ":"
    18.83
    ","
    total_c98
    ":"
    0.000000000000000000
    ","
    in_use_c98
    ":"
    0.00000000
    ","
    available_c98
    ":"
    0.00000000
    ","
    xcoin_last_c9
    8
    ":"
    364
    ","
    total_med
    ":"
    0.00000000
    ","
    in_use_med
    ":"
    0.00000000
    ","
    available_med
    ":"
    0.00000000
    ","
    xcoin_last_med
    ":"
    16.94
    ","
    total_sgb
    ":"
    0.0000000000000000
    00
    ","
    in_use_sgb
    ":"
    0.00000000
    ","
    available_sgb
    ":"
    0.00000000
    ","
    xcoin_last_sgb
    ":"
    0
    ","
    total_1inch
    ":"
    0.000000000000000000
    ","
    in_use_1inch
    ":"
    0.00000000
    ",
    "available_1inch": "0.00000000",
    "xcoin_last_1inch": "584",
    "total_crv": "0.000000000000000000",
    "in_use_crv": "0.00000000",
    "available_crv": "0.00000000",
    "xcoin_last_crv": "832",
    "total_boba": "0.000000000000000000",
    "in_use_boba": "0.00000000",
    "available_boba": "0.00000000",
    "xcoin_last_boba": "354",
    "tot
    al_rpg
    ":"
    0.157000000000000000
    ","
    in_use_rpg
    ":"
    0.00000000
    ","
    available_rpg
    ":"
    0.15700000
    ","
    xcoin_last_rpg
    ":"
    0
    ","
    total_dydx
    ":"
    0.000000000000000000
    ","
    i
    n_use_dydx
    ":"
    0.00000000
    ","
    available_dydx
    ":"
    0.00000000
    ","
    xcoin_last_dydx
    ":"
    4070
    ","
    total_mina
    ":"
    0.000000000
    ","
    in_use_mina
    ":"
    0.00000000
    ","
    available_
    mina
    ":"
    0.00000000
    ","
    xcoin_last_mina
    ":"
    1871
    ","
    total_flow
    ":"
    0.00000000
    ","
    in_use_flow
    ":"
    0.00000000
    ","
    available_flow
    ":"
    0.00000000
    ","
    xcoin_last_flow
    ":
    "1241",
    "total_joe": "0.000000000000000000",
    "in_use_joe": "0.00000000",
    "available_joe": "0.00000000",
    "xcoin_last_joe": "839",
    "total_gala": "0.00000000",
    "in_use_gala": "0.00000000",
    "available_gala": "0.00000000",
    "xcoin_last_gala": "41.66",
    "total_ens": "0.000000000000000000",
    "in_use_ens": "0.00000000",
    "available_ens": "0.00000000",
    "xcoin_last_ens": "0.0002269",
    "total_purse": "0.000000000000000000",
    "in_use_purse": "0.00000000",
    "available_purse": "0.0
    0000000
    ","
    xcoin_last_purse
    ":"
    0
    ","
    total_btt
    ":"
    0.001170000000000000
    ","
    in_use_btt
    ":"
    0.00000000
    ","
    available_btt
    ":"
    0.00117000
    ","
    xcoin_last_btt
    ":"
    0.001
    6
    ","
    total_efi
    ":"
    0.000000000000000000
    ","
    in_use_efi
    ":"
    0.00000000
    ","
    available_efi
    ":"
    0.00000000
    ","
    xcoin_last_efi
    ":"
    0
    ","
    total_jasmy
    ":"
    0.00000000000000
    0000
    ","
    in_use_jasmy
    ":"
    0.00000000
    ","
    available_jasmy
    ":"
    0.00000000
    ","
    xcoin_last_jasmy
    ":"
    9.005
    ","
    total_titan
    ":"
    0.000000000000000000
    ","
    in_use_titan
    ":"
    0.00000000
    ","
    available_titan
    ":"
    0.00000000
    ","
    xcoin_last_titan
    ":"
    0
    ","
    total_req
    ":"
    0.000000000000000000
    ","
    in_use_req
    ":"
    0.00000000
    ","
    available_req
    ":"
    0
    .00000000
    ","
    xcoin_last_req
    ":"
    129
    ","
    total_cspr
    ":"
    0.000000000
    ","
    in_use_cspr
    ":"
    0.00000000
    ","
    available_cspr
    ":"
    0.00000000
    ","
    xcoin_last_cspr
    ":"
    69
    ","
    tot
    al_solo
    ":"
    0.000000000000000
    ","
    in_use_solo
    ":"
    0.00000000
    ","
    available_solo
    ":"
    0.00000000
    ","
    xcoin_last_solo
    ":"
    0
    ","
    total_avax
    ":"
    0.000000000000000000
    ","
    in_use_avax
    ":"
    0.00000000
    ","
    available_avax
    ":"
    0.00000000
    ","
    xcoin_last_avax
    ":"
    52800
    ","
    total_tdrop
    ":"
    0.000000000000000000
    ","
    in_use_tdrop
    ":"
    0.00000000
    ","
    available_tdrop
    ":"
    0.00000000
    ","
    xcoin_last_tdrop
    ":"
    2.54
    ","
    total_hbar
    ":"
    0.00000000
    ","
    in_use_hbar
    ":"
    0.00000000
    ","
    available_hbar
    ":"
    0.00000000
    ","
    xc
    oin_last_hbar
    ":"
    118
    ","
    total_fanc
    ":"
    0.000000000000000000
    ","
    in_use_fanc
    ":"
    0.00000000
    ","
    available_fanc
    ":"
    0.00000000
    ","
    xcoin_last_fanc
    ":"
    19.19
    ","
    tota
    l_sprt
    ":"
    0.000000000000000000
    ","
    in_use_sprt
    ":"
    0.00000000
    ","
    available_sprt
    ":"
    0.00000000
    ","
    xcoin_last_sprt
    ":"
    0
    ","
    total_npt
    ":"
    0.000000000000000000
    ",
    "in_use_npt": "0.00000000",
    "available_npt": "0.00000000",
    "xcoin_last_npt": "602",
    "total_witch": "0.000000000000000000",
    "in_use_witch": "0.00000000",
    "a
    vailable_witch
    ":"
    0.00000000
    ","
    xcoin_last_witch
    ":"
    0.00000419
    ","
    total_rei
    ":"
    0.000000000000000000
    ","
    in_use_rei
    ":"
    0.00000000
    ","
    available_rei
    ":"
    0.0000
    0000
    ","
    xcoin_last_rei
    ":"
    44.16
    ","
    total_t
    ":"
    0.000000000000000000
    ","
    in_use_t
    ":"
    0.00000000
    ","
    available_t
    ":"
    0.00000000
    ","
    xcoin_last_t
    ":"
    33.97
    ","
    total_
    aqua
    ":"
    0.000000000000000000
    ","
    in_use_aqua
    ":"
    0.00000000
    ","
    available_aqua
    ":"
    0.00000000
    ","
    xcoin_last_aqua
    ":"
    0
    ","
    total_mbx
    ":"
    0.000000006731365093
    ","
    i
    n_use_mbx
    ":"
    0.00000000
    ","
    available_mbx
    ":"
    0.00000000
    ","
    xcoin_last_mbx
    ":"
    1047
    ","
    total_gmt
    ":"
    0.00000000
    ","
    in_use_gmt
    ":"
    0.00000000
    ","
    available_gmt
    ":"
    0.00000000
    ","
    xcoin_last_gmt
    ":"
    440
    ","
    total_tava
    ":"
    0.000000000000000000
    ","
    in_use_tava
    ":"
    0.00000000
    ","
    available_tava
    ":"
    0.00000000
    ","
    xcoin_last_tava
    ": "100",
    "total_dar": "0.00000000",
    "in_use_dar": "0.00000000",
    "available_dar": "0.00000000",
    "xcoin_last_dar": "206",
    "total_ape": "0.000000000000000000",
    "in_use_ape": "0.00000000",
    "available_ape": "0.00000000",
    "xcoin_last_ape": "2238",
    "total_wncg": "0.000000000000000000",
    "in_use_wncg": "0.00000000",
    "av
    ailable_wncg
    ":"
    0.00000000
    ","
    xcoin_last_wncg
    ":"
    149
    ","
    total_alt
    ":"
    0.000000000000000000
    ","
    in_use_alt
    ":"
    0.00000000
    ","
    available_alt
    ":"
    0.00000000
    ","
    xco
    in_last_alt
    ":"
    337
    ","
    total_xcn
    ":"
    0.000000000000000000
    ","
    in_use_xcn
    ":"
    0.00000000
    ","
    available_xcn
    ":"
    0.00000000
    ","
    xcoin_last_xcn
    ":"
    2.076
    ","
    total_gxa
    ": "0.000000000000000000",
    "in_use_gxa": "0.00000000",
    "available_gxa": "0.00000000",
    "xcoin_last_gxa": "9.001",
    "total_luna2": "0.00000000",
    "in_use_luna2": "0.00000000",
    "available_luna2": "0.00000000",
    "xcoin_last_luna2": "0",
    "total_talk": "0.000000000000000000",
    "in_use_talk": "0.00000000",
    "available_tal
    k
    ":"
    0.00000000
    ","
    xcoin_last_talk
    ":"
    0.0000011
    ","
    total_ogv
    ":"
    0.000000000000000000
    ","
    in_use_ogv
    ":"
    0.00000000
    ","
    available_ogv
    ":"
    0.00000000
    ","
    xcoin_la
    st_ogv
    ":"
    0
    ","
    total_azit
    ":"
    0.000000000000000000
    ","
    in_use_azit
    ":"
    0.00000000
    ","
    available_azit
    ":"
    0.00000000
    ","
    xcoin_last_azit
    ":"
    68.57
    ","
    total_ethw
    ":"
    0.000000000000000000
    ","
    in_use_ethw
    ":"
    0.00000000
    ","
    available_ethw
    ":"
    0.00000000
    ","
    xcoin_last_ethw
    ":"
    0
    ","
    total_ethf
    ":"
    0.000000000000000000
    ","
    in_use_
    ethf
    ":"
    0.00000000
    ","
    available_ethf
    ":"
    0.00000000
    ","
    xcoin_last_ethf
    ":"
    0
    ","
    total_flr
    ":"
    0.000000000000000000
    ","
    in_use_flr
    ":"
    0.00000000
    ","
    available_fl
    r
    ":"
    0.00000000
    ","
    xcoin_last_flr
    ":"
    23.86
    ","
    total_icz
    ":"
    0.000000000000000000
    ","
    in_use_icz
    ":"
    0.00000000
    ","
    available_icz
    ":"
    0.00000000
    ","
    xcoin_last_ic
    z
    ":"
    0
    ","
    total_sfp
    ":"
    0.000000000000000000
    ","
    in_use_sfp
    ":"
    0.00000000
    ","
    available_sfp
    ":"
    0.00000000
    ","
    xcoin_last_sfp
    ":"
    1053
    ","
    total_fitfi
    ":"
    0.0000000
    00000000000
    ","
    in_use_fitfi
    ":"
    0.00000000
    ","
    available_fitfi
    ":"
    0.00000000
    ","
    xcoin_last_fitfi
    ":"
    10.85
    ","
    total_stat
    ":"
    0.000000000000000000
    ","
    in_use_st
    at
    ":"
    0.00000000
    ","
    available_stat
    ":"
    0.00000000
    ","
    xcoin_last_stat
    ":"
    137
    ","
    total_crts
    ":"
    0.000000000000000000
    ","
    in_use_crts
    ":"
    0.00000000
    ","
    available_
    crts
    ":"
    0.00000000
    ","
    xcoin_last_crts
    ":"
    0.3385
    ","
    total_vix
    ":"
    0.000000000000000000
    ","
    in_use_vix
    ":"
    0.00000000
    ","
    available_vix
    ":"
    0.00000000
    ","
    xcoin_la
    st_vix
    ":"
    11.21
    ","
    total_lbl
    ":"
    0.000000000000000000
    ","
    in_use_lbl
    ":"
    0.00000000
    ","
    available_lbl
    ":"
    0.00000000
    ","
    xcoin_last_lbl
    ":"
    3.797
    ","
    total_flz
    ":"
    0
    .000000000000000000
    ","
    in_use_flz
    ":"
    0.00000000
    ","
    available_flz
    ":"
    0.00000000
    ","
    xcoin_last_flz
    ":"
    3525
    ","
    total_berry
    ":"
    0.000000000000000000
    ","
    in_use_
    berry
    ":"
    0.00000000
    ","
    available_berry
    ":"
    0.00000000
    ","
    xcoin_last_berry
    ":"
    0.00000001
    ","
    total_lm
    ":"
    0.000000000000000000
    ","
    in_use_lm
    ":"
    0.00000000
    ","
    av
    ailable_lm
    ":"
    0.00000000
    ","
    xcoin_last_lm
    ":"
    11.04
    ","
    total_grnd
    ":"
    0.000000000000000000
    ","
    in_use_grnd
    ":"
    0.00000000
    ","
    available_grnd
    ":"
    0.00000000
    ","
    xc
    oin_last_grnd
    ":"
    199
    ","
    total_apt
    ":"
    0.00000000
    ","
    in_use_apt
    ":"
    0.00000000
    ","
    available_apt
    ":"
    0.00000000
    ","
    xcoin_last_apt
    ":"
    12810
    ","
    total_blur
    ":"
    7041.
    444700000000000000
    ","
    in_use_blur
    ":"
    7041.44470000
    ","
    available_blur
    ":"
    0.00000000
    ","
    xcoin_last_blur
    ":"
    629
    ","
    total_wemix
    ":"
    0.000043959713404669
    ","
    in_
    use_wemix
    ":"
    0.00000000
    ","
    available_wemix
    ":"
    0.00004395
    ","
    xcoin_last_wemix
    ":"
    3426
    ","
    total_news
    ":"
    0.000000000
    ","
    in_use_news
    ":"
    0.00000000
    ","
    available
    _news
    ":"
    0.00000000
    ","
    xcoin_last_news
    ":"
    0.00000001
    ","
    total_op_eth
    ":"
    0.000000000000000000
    ","
    in_use_op_eth
    ":"
    0.00000000
    ","
    available_op_eth
    ":"
    0.00000
    000
    ","
    xcoin_last_op_eth
    ":"
    0
    ","
    total_dice
    ":"
    0.000000000000000000
    ","
    in_use_dice
    ":"
    0.00000000
    ","
    available_dice
    ":"
    0.00000000
    ","
    xcoin_last_dice
    ":"
    0.00
    000036
    ","
    total_oas
    ":"
    0.000000000000000000
    ","
    in_use_oas
    ":"
    0.00000000
    ","
    available_oas
    ":"
    0.00000000
    ","
    xcoin_last_oas
    ":"
    128
    ","
    total_hook
    ":"
    0.00000000
    0000000000
    ","
    in_use_hook
    ":"
    0.00000000
    ","
    available_hook
    ":"
    0.00000000
    ","
    xcoin_last_hook
    ":"
    1709
    ","
    total_entc
    ":"
    0.000000000000000000
    ","
    in_use_entc
    ":"
    0.00000000
    ","
    available_entc
    ":"
    0.00000000
    ","
    xcoin_last_entc
    ":"
    233
    ","
    total_onit
    ":"
    0.000000000000000000
    ","
    in_use_onit
    ":"
    0.00000000
    ","
    available_onit
    ": "0.00000000",
    "xcoin_last_onit": "39.27",
    "total_op": "0.000000000000000000",
    "in_use_op": "0.00000000",
    "available_op": "0.00000000",
    "xcoin_last_op": "5
    135
    ","
    total_arb_eth
    ":"
    0.000000000000000000
    ","
    in_use_arb_eth
    ":"
    0.00000000
    ","
    available_arb_eth
    ":"
    0.00000000
    ","
    xcoin_last_arb_eth
    ":"
    0
    ","
    total_roa
    ":"
    0.000000000
    ","
    in_use_roa
    ":"
    0.00000000
    ","
    available_roa
    ":"
    0.00000000
    ","
    xcoin_last_roa
    ":"
    103
    ","
    total_orb
    ":"
    0.000000000000000000
    ","
    in_use_orb
    ":"
    0.000
    00000
    ","
    available_orb
    ":"
    0.00000000
    ","
    xcoin_last_orb
    ":"
    0.00000112
    ","
    total_ever
    ":"
    0.000000000
    ","
    in_use_ever
    ":"
    0.00000000
    ","
    available_ever
    ":"
    0.00000
    000
    ","
    xcoin_last_ever
    ":"
    34.52
    ","
    total_gmx
    ":"
    0.000000000000000000
    ","
    in_use_gmx
    ":"
    0.00000000
    ","
    available_gmx
    ":"
    0.00000000
    ","
    xcoin_last_gmx
    ":"
    74900
    ",
    "total_stx": "0.00000000",
    "in_use_stx": "0.00000000",
    "available_stx": "0.00000000",
    "xcoin_last_stx": "2033",
    "total_xpla": "0.000000000000000000",
    "in_
    use_xpla
    ":"
    0.00000000
    ","
    available_xpla
    ":"
    0.00000000
    ","
    xcoin_last_xpla
    ":"
    302
    ","
    total_reap
    ":"
    0.000000000000000000
    ","
    in_use_reap
    ":"
    0.00000000
    ","
    avai
    lable_reap
    ":"
    0.00000000
    ","
    xcoin_last_reap
    ":"
    0.00000011
    ","
    total_aht
    ":"
    0.000000000000000000
    ","
    in_use_aht
    ":"
    0.00000000
    ","
    available_aht
    ":"
    0.00000000
    ",
    "xcoin_last_aht": "0.00000017",
    "total_arb": "0.000000000000000000",
    "in_use_arb": "0.00000000",
    "available_arb": "0.00000000",
    "xcoin_last_arb": "2111",
    "total_inj": "0.000000000000000000",
    "in_use_inj": "0.00000000",
    "available_inj": "0.00000000",
    "xcoin_last_inj": "49250",
    "total_hft": "0.000000000000000
    000
    ","
    in_use_hft
    ":"
    0.00000000
    ","
    available_hft
    ":"
    0.00000000
    ","
    xcoin_last_hft
    ":"
    512
    ","
    total_rpl
    ":"
    0.000000000000000000
    ","
    in_use_rpl
    ":"
    0.00000000
    ","
    available_rpl
    ":"
    0.00000000
    ","
    xcoin_last_rpl
    ":"
    40530
    ","
    total_gpt
    ":"
    0.000000000000000000
    ","
    in_use_gpt
    ":"
    0.00000000
    ","
    available_gpt
    ":"
    0.00000000
    ","
    x
    coin_last_gpt
    ":"
    0
    ","
    total_imx
    ":"
    0.000000000000000000
    ","
    in_use_imx
    ":"
    0.00000000
    ","
    available_imx
    ":"
    0.00000000
    ","
    xcoin_last_imx
    ":"
    2945
    ","
    total_cfx
    ":
    "0.000000000000000000",
    "in_use_cfx": "0.00000000",
    "available_cfx": "0.00000000",
    "xcoin_last_cfx": "262",
    "total_acs": "0.00000000",
    "in_use_acs": "0.000
    00000
    ","
    available_acs
    ":"
    0.00000000
    ","
    xcoin_last_acs
    ":"
    4.126
    ","
    total_fxs
    ":"
    0.000000000000000000
    ","
    in_use_fxs
    ":"
    0.00000000
    ","
    available_fxs
    ":"
    0.0000
    0000
    ","
    xcoin_last_fxs
    ":"
    11660
    ","
    total_celo
    ":"
    0.000000000000000000
    ","
    in_use_celo
    ":"
    0.00000000
    ","
    available_celo
    ":"
    0.00000000
    ","
    xcoin_last_celo
    ":"
    10
    50
    ","
    total_ldo
    ":"
    0.000000000000000000
    ","
    in_use_ldo
    ":"
    0.00000000
    ","
    available_ldo
    ":"
    0.00000000
    ","
    xcoin_last_ldo
    ":"
    3564
    ","
    total_ftm
    ":"
    0.000000000000
    000000
    ","
    in_use_ftm
    ":"
    0.00000000
    ","
    available_ftm
    ":"
    0.00000000
    ","
    xcoin_last_ftm
    ":"
    650
    ","
    total_fet
    ":"
    0.000000000000000000
    ","
    in_use_fet
    ":"
    0.00000000
    ","
    available_fet
    ":"
    0.00000000
    ","
    xcoin_last_fet
    ":"
    927
    ","
    total_sui
    ":"
    1830.312100000
    ","
    in_use_sui
    ":"
    0.00000000
    ","
    available_sui
    ":"
    1830.31210000
    ","
    xco
    in_last_sui
    ":"
    1070
    ","
    total_kwenta
    ":"
    0.000000000000000000
    ","
    in_use_kwenta
    ":"
    0.00000000
    ","
    available_kwenta
    ":"
    0.00000000
    ","
    xcoin_last_kwenta
    ":"
    0.002
    70944
    ","
    total_lazio
    ":"
    0.00000000
    ","
    in_use_lazio
    ":"
    0.00000000
    ","
    available_lazio
    ":"
    0.00000000
    ","
    xcoin_last_lazio
    ":"
    0.00004193
    ","
    total_nct
    ":"
    0.00000
    0000000000000
    ","
    in_use_nct
    ":"
    0.00000000
    ","
    available_nct
    ":"
    0.00000000
    ","
    xcoin_last_nct
    ":"
    16.23
    ","
    total_porto
    ":"
    0.00000000
    ","
    in_use_porto
    ":"
    0.00000
    000
    ","
    available_porto
    ":"
    0.00000000
    ","
    xcoin_last_porto
    ":"
    0.00004598
    ","
    total_xcore
    ":"
    0.000000000000000
    ","
    in_use_xcore
    ":"
    0.00000000
    ","
    available_xcor
    e
    ":"
    0.00000000
    ","
    xcoin_last_xcore
    ":"
    0
    ","
    total_floki
    ":"
    0.000000000
    ","
    in_use_floki
    ":"
    0.00000000
    ","
    available_floki
    ":"
    0.00000000
    ","
    xcoin_last_floki
    ":
    "0.048",
    "total_alex": "0.00000000",
    "in_use_alex": "0.00000000",
    "available_alex": "0.00000000",
    "xcoin_last_alex": "458",
    "total_id": "0.0000000000000000
    00
    ","
    in_use_id
    ":"
    0.00000000
    ","
    available_id
    ":"
    0.00000000
    ","
    xcoin_last_id
    ":"
    419
    ","
    total_rndr
    ":"
    0.000000000000000000
    ","
    in_use_rndr
    ":"
    0.00000000
    ","
    av
    ailable_rndr
    ":"
    0.00000000
    ","
    xcoin_last_rndr
    ":"
    6085
    ","
    total_stg
    ":"
    0.000000000000000000
    ","
    in_use_stg
    ":"
    0.00000000
    ","
    available_stg
    ":"
    0.00000000
    ","
    xc
    oin_last_stg
    ":"
    835
    ","
    total_santos
    ":"
    0.00000000
    ","
    in_use_santos
    ":"
    0.00000000
    ","
    available_santos
    ":"
    0.00000000
    ","
    xcoin_last_santos
    ":"
    0.00006608
    ","
    to
    tal_osmo
    ":"
    0.00000000
    ","
    in_use_osmo
    ":"
    0.00000000
    ","
    available_osmo
    ":"
    0.00000000
    ","
    xcoin_last_osmo
    ":"
    2069
    ","
    total_gal
    ":"
    0.000000000000000000
    ","
    in_u
    se_gal
    ":"
    0.00000000
    ","
    available_gal
    ":"
    0.00000000
    ","
    xcoin_last_gal
    ":"
    3098
    ","
    total_ilv
    ":"
    0.000000000000000000
    ","
    in_use_ilv
    ":"
    0.00000000
    ","
    available
    _ilv
    ":"
    0.00000000
    ","
    xcoin_last_ilv
    ":"
    123500
    ","
    total_mav
    ":"
    0.000000000000000000
    ","
    in_use_mav
    ":"
    0.00000000
    ","
    available_mav
    ":"
    0.00000000
    ","
    xcoin_las
    t_mav
    ":"
    533
    ","
    total_hvh
    ":"
    0.000000000000000000
    ","
    in_use_hvh
    ":"
    0.00000000
    ","
    available_hvh
    ":"
    0.00000000
    ","
    xcoin_last_hvh
    ":"
    0.00000055
    ","
    total_rss3
    ": "0.000000000000000000",
    "in_use_rss3": "0.00000000",
    "available_rss3": "0.00000000",
    "xcoin_last_rss3": "165",
    "total_audio": "0.000000000000000000",
    "in
    _use_audio
    ":"
    0.00000000
    ","
    available_audio
    ":"
    0.00000000
    ","
    xcoin_last_audio
    ":"
    351
    ","
    total_agi
    ":"
    0.000000000000000000
    ","
    in_use_agi
    ":"
    0.00000000
    ","
    av
    ailable_agi
    ":"
    0.00000000
    ","
    xcoin_last_agi
    ":"
    72.8
    ","
    total_rdnt
    ":"
    0.000000000000000000
    ","
    in_use_rdnt
    ":"
    0.00000000
    ","
    available_rdnt
    ":"
    0.00000000
    ","
    x
    coin_last_rdnt
    ":"
    416
    ","
    total_astr
    ":"
    0.000000000000000000
    ","
    in_use_astr
    ":"
    0.00000000
    ","
    available_astr
    ":"
    0.00000000
    ","
    xcoin_last_astr
    ":"
    187
    ","
    total
    _wld
    ":"
    0.000000000000000000
    ","
    in_use_wld
    ":"
    0.00000000
    ","
    available_wld
    ":"
    0.00000000
    ","
    xcoin_last_wld
    ":"
    5015
    ","
    total_flux
    ":"
    0.00000000
    ","
    in_use_flu
    x
    ":"
    0.00000000
    ","
    available_flux
    ":"
    0.00000000
    ","
    xcoin_last_flux
    ":"
    859
    ","
    total_rvn
    ":"
    0.00000000
    ","
    in_use_rvn
    ":"
    0.00000000
    ","
    available_rvn
    ":"
    0.00000
    000
    ","
    xcoin_last_rvn
    ":"
    28.86
    ","
    total_lever
    ":"
    0.000000000000000000
    ","
    in_use_lever
    ":"
    0.00000000
    ","
    available_lever
    ":"
    0.00000000
    ","
    xcoin_last_lever
    ":
    "2.308",
    "total_edu": "0.000000000000000000",
    "in_use_edu": "0.00000000",
    "available_edu": "0.00000000",
    "xcoin_last_edu": "968",
    "total_sei": "0.00000000",
    "in_use_sei": "0.00000000",
    "available_sei": "0.00000000",
    "xcoin_last_sei": "781",
    "total_moc": "0.000000000000000000",
    "in_use_moc": "0.00000000",
    "avai
    lable_moc
    ":"
    0.00000000
    ","
    xcoin_last_moc
    ":"
    123
    ","
    total_pepe
    ":"
    0.000000000000000000
    ","
    in_use_pepe
    ":"
    0.00000000
    ","
    available_pepe
    ":"
    0.00000000
    ","
    xcoi
    n_last_pepe
    ":"
    0.0017
    ","
    total_cyber
    ":"
    0.000000000000000000
    ","
    in_use_cyber
    ":"
    0.00000000
    ","
    available_cyber
    ":"
    0.00000000
    ","
    xcoin_last_cyber
    ":"
    9375
    ","
    total_arkm
    ":"
    0.000000000000000000
    ","
    in_use_arkm
    ":"
    0.00000000
    ","
    available_arkm
    ":"
    0.00000000
    ","
    xcoin_last_arkm
    ":"
    820
    ","
    total_pyr
    ":"
    0.00000000000000
    0000
    ","
    in_use_pyr
    ":"
    0.00000000
    ","
    available_pyr
    ":"
    0.00000000
    ","
    xcoin_last_pyr
    ":"
    11590
    ","
    total_iotx
    ":"
    0.000000000000000000
    ","
    in_use_iotx
    ":"
    0.000000
    00
    ","
    available_iotx
    ":"
    0.00000000
    ","
    xcoin_last_iotx
    ":"
    69.21
    ","
    total_high
    ":"
    0.000000000000000000
    ","
    in_use_high
    ":"
    0.00000000
    ","
    available_high
    ":"
    0.00
    000000
    ","
    xcoin_last_high
    ":"
    2272
    ","
    total_pendle
    ":"
    0.000000000000000000
    ","
    in_use_pendle
    ":"
    0.00000000
    ","
    available_pendle
    ":"
    0.00000000
    ","
    xcoin_last_p
    endle
    ":"
    1621
    ","
    total_storj
    ":"
    0.00000000
    ","
    in_use_storj
    ":"
    0.00000000
    ","
    available_storj
    ":"
    0.00000000
    ","
    xcoin_last_storj
    ":"
    964
    ","
    total_api3
    ":"
    0.0000
    00000000000000
    ","
    in_use_api3
    ":"
    0.00000000
    ","
    available_api3
    ":"
    0.00000000
    ","
    xcoin_last_api3
    ":"
    2752
    ","
    total_ztx
    ":"
    0.000000000000000000
    ","
    in_use_ztx
    ": "0.00000000",
    "available_ztx": "0.00000000",
    "xcoin_last_ztx": "30.58",
    "total_tia": "0.00000000",
    "in_use_tia": "0.00000000",
    "available_tia": "0.0000000
    0
    ","
    xcoin_last_tia
    ":"
    16130
    ","
    total_spurs
    ":"
    0.00000000
    ","
    in_use_spurs
    ":"
    0.00000000
    ","
    available_spurs
    ":"
    0.00000000
    ","
    xcoin_last_spurs
    ":"
    5150
    ","
    tota
    l_chz_m
    ":"
    0.000000000000000000
    ","
    in_use_chz_m
    ":"
    0.00000000
    ","
    available_chz_m
    ":"
    0.00000000
    ","
    xcoin_last_chz_m
    ":"
    0
    ","
    total_hifi
    ":"
    0.000000000000000
    000
    ","
    in_use_hifi
    ":"
    0.00000000
    ","
    available_hifi
    ":"
    0.00000000
    ","
    xcoin_last_hifi
    ":"
    1005
    ","
    total_bigtime
    ":"
    0.000000000000000000
    ","
    in_use_bigtime
    ":"
    0
    .00000000
    ","
    available_bigtime
    ":"
    0.00000000
    ","
    xcoin_last_bigtime
    ":"
    674
    ","
    total_stmx
    ":"
    0.000000000000000000
    ","
    in_use_stmx
    ":"
    0.00000000
    ","
    available_
    stmx
    ":"
    0.00000000
    ","
    xcoin_last_stmx
    ":"
    12.01
    ","
    total_usdt
    ":"
    0.00000000
    ","
    in_use_usdt
    ":"
    0.00000000
    ","
    available_usdt
    ":"
    0.00000000
    ","
    xcoin_last_usdt
    ": "1346",
    "total_usdc": "0.00000000",
    "in_use_usdc": "0.00000000",
    "available_usdc": "0.00000000",
    "xcoin_last_usdc": "1346",
    "total_ace": "0.00000000000000
    0000
    ","
    in_use_ace
    ":"
    0.00000000
    ","
    available_ace
    ":"
    0.00000000
    ","
    xcoin_last_ace
    ":"
    12940
    ","
    total_c9472
    ":"
    0.000000000000000000
    ","
    in_use_c9472
    ":"
    0.00000000
    ","
    available_c9472
    ":"
    0.00000000
    ","
    xcoin_last_c9472
    ":"
    0
    "}}

